Metadata-Version: 1.1
Name: EGCG-Core
Version: 0.10
Summary: Shared functionality across EGCG projects
Home-page: https://github.com/EdinburghGenomics/EGCG-Core
Author: Murray Wham
Author-email: murray.wham@ed.ac.uk
License: MIT
Keywords: EdinburghGenomics executor notification logging api rest
Platform: UNKNOWN
Classifier: Development Status :: 4 - Beta
Classifier: Environment :: Console
Classifier: Intended Audience :: Developers
Classifier: Intended Audience :: Healthcare Industry
Classifier: Intended Audience :: Science/Research
Classifier: Operating System :: POSIX :: Linux
Classifier: Programming Language :: Python :: 3
Classifier: Programming Language :: Python :: 3.3
Classifier: Programming Language :: Python :: 3.4
Classifier: Programming Language :: Python :: 3.6
Requires: pytest(==4.1.1)
Requires: pytest_xdist(==1.24.1)
Requires: pytest_cov(==2.6.1)
Requires: requests(==2.20.0)
Requires: PyYAML(==5.1b3)
Requires: pyclarity_lims(==0.4.5)
Requires: jinja2(==2.8)
Requires: asana(==0.6.7)
Requires: cached_property(==1.5.1)
